deepbio/__init__.py
deepbio/version.py
deepbio/_vendor/AAdata.RData
deepbio/data/__init__.py
deepbio/data/data_loader.py
deepbio/data/dataset.py
deepbio/feat/__init__.py
deepbio/feat/featurizer.py
deepbio/feat/ohe.py
deepbio/model/__init__.py
deepbio/model/basset.py
deepbio/model/model.py
deepbio/utils/__init__.py
deepbio/utils/constants.py
deepbio-0.0.1.dist-info/METADATA
deepbio-0.0.1.dist-info/WHEEL
deepbio-0.0.1.dist-info/top_level.txt
deepbio-0.0.1.dist-info/RECORD
